README.md
setup.cfg
setup.py
pyfolio_fork_aprm/__init__.py
pyfolio_fork_aprm/_seaborn.py
pyfolio_fork_aprm/bayesian.py
pyfolio_fork_aprm/capacity.py
pyfolio_fork_aprm/deprecate.py
pyfolio_fork_aprm/interesting_periods.py
pyfolio_fork_aprm/ipycompat.py
pyfolio_fork_aprm/perf_attrib.py
pyfolio_fork_aprm/plotting.py
pyfolio_fork_aprm/pos.py
pyfolio_fork_aprm/risk.py
pyfolio_fork_aprm/round_trips.py
pyfolio_fork_aprm/tears.py
pyfolio_fork_aprm/timeseries.py
pyfolio_fork_aprm/txn.py
pyfolio_fork_aprm/utils.py
pyfolio_fork_aprm.egg-info/PKG-INFO
pyfolio_fork_aprm.egg-info/SOURCES.txt
pyfolio_fork_aprm.egg-info/dependency_links.txt
pyfolio_fork_aprm.egg-info/requires.txt
pyfolio_fork_aprm.egg-info/top_level.txt