Metadata-Version: 2.1
Name: pyfolio-fork-aprm
Version: 0.8.2
Summary: If you're looking for pyfolio you've come to the wrong place.
Home-page: https://github.com/quantopian/pyfolio
Maintainer: Kevin Heavey
Maintainer-email: kevinheavey123@gmail.com
License: Apache License, Version 2.0
Platform: UNKNOWN
Classifier: Development Status :: 4 - Beta
Classifier: Programming Language :: Python
Classifier: Programming Language :: Python :: 2
Classifier: Programming Language :: Python :: 3
Classifier: Programming Language :: Python :: 2.7
Classifier: Programming Language :: Python :: 3.4
Classifier: Programming Language :: Python :: 3.5
Classifier: License :: OSI Approved :: Apache Software License
Classifier: Intended Audience :: Science/Research
Classifier: Topic :: Scientific/Engineering
Classifier: Topic :: Scientific/Engineering :: Mathematics
Classifier: Operating System :: OS Independent
Provides-Extra: test
Provides-Extra: all
Provides-Extra: bayesian
